{
	"id": "3ZEKp85dx9slQyM",
	"json": "{\"id\":\"3ZEKp85dx9slQyM\",\"url\":\"https://9anime.vc/az-list/?page=77\",\"loadedUrl\":\"https://9anime.vc/az-list/?page=77\",\"uniqueKey\":\"https://9anime.vc/az-list?page=77\",\"method\":\"GET\",\"noRetry\":false,\"retryCount\":0,\"errorMessages\":[],\"headers\":{},\"userData\":{\"label\":\"manga_list_page\"},\"handledAt\":\"2022-09-28T19:21:46.293Z\"}",
	"method": "GET",
	"orderNo": null,
	"retryCount": 0,
	"uniqueKey": "https://9anime.vc/az-list?page=77",
	"url": "https://9anime.vc/az-list/?page=77"
}