{
	"id": "2YR7pXDSjsTxhMf",
	"json": "{\"id\":\"2YR7pXDSjsTxhMf\",\"url\":\"https://www.brmangas.net/manga/zero-in-online/\",\"loadedUrl\":\"https://www.brmangas.net/manga/zero-in-online/\",\"uniqueKey\":\"https://www.brmangas.net/manga/zero-in-online\",\"method\":\"GET\",\"noRetry\":false,\"retryCount\":0,\"errorMessages\":[],\"headers\":{},\"userData\":{\"label\":\"manga_page\"},\"handledAt\":\"2022-09-27T18:53:26.554Z\"}",
	"method": "GET",
	"orderNo": null,
	"retryCount": 0,
	"uniqueKey": "https://www.brmangas.net/manga/zero-in-online",
	"url": "https://www.brmangas.net/manga/zero-in-online/"
}