{
	"id": "79vcLVg7F5kneHY",
	"json": "{\"id\":\"79vcLVg7F5kneHY\",\"url\":\"https://www.brmangas.net/manga/an-adults-experiences-online/\",\"loadedUrl\":\"https://www.brmangas.net/manga/an-adults-experiences-online/\",\"uniqueKey\":\"https://www.brmangas.net/manga/an-adults-experiences-online\",\"method\":\"GET\",\"noRetry\":false,\"retryCount\":0,\"errorMessages\":[],\"headers\":{},\"userData\":{\"label\":\"manga_page\"},\"handledAt\":\"2022-09-27T18:51:56.122Z\"}",
	"method": "GET",
	"orderNo": null,
	"retryCount": 0,
	"uniqueKey": "https://www.brmangas.net/manga/an-adults-experiences-online",
	"url": "https://www.brmangas.net/manga/an-adults-experiences-online/"
}