{
	"id": "9q0JURDQe7NMwEH",
	"json": "{\"id\":\"9q0JURDQe7NMwEH\",\"url\":\"https://www.brmangas.net/manga/the-strongest-king-online/\",\"loadedUrl\":\"https://www.brmangas.net/manga/the-strongest-king-online/\",\"uniqueKey\":\"https://www.brmangas.net/manga/the-strongest-king-online\",\"method\":\"GET\",\"noRetry\":false,\"retryCount\":0,\"errorMessages\":[],\"headers\":{},\"userData\":{\"label\":\"manga_page\"},\"handledAt\":\"2022-09-27T18:51:06.626Z\"}",
	"method": "GET",
	"orderNo": null,
	"retryCount": 0,
	"uniqueKey": "https://www.brmangas.net/manga/the-strongest-king-online",
	"url": "https://www.brmangas.net/manga/the-strongest-king-online/"
}