{
	"id": "b3SEOQR0s7XZUJ2",
	"json": "{\"id\":\"b3SEOQR0s7XZUJ2\",\"url\":\"https://www.brmangas.net/manga/boku-wa-ookami-online/\",\"loadedUrl\":\"https://www.brmangas.net/manga/boku-wa-ookami-online/\",\"uniqueKey\":\"https://www.brmangas.net/manga/boku-wa-ookami-online\",\"method\":\"GET\",\"noRetry\":false,\"retryCount\":0,\"errorMessages\":[],\"headers\":{},\"userData\":{\"label\":\"manga_page\"},\"handledAt\":\"2022-09-27T18:54:09.346Z\"}",
	"method": "GET",
	"orderNo": null,
	"retryCount": 0,
	"uniqueKey": "https://www.brmangas.net/manga/boku-wa-ookami-online",
	"url": "https://www.brmangas.net/manga/boku-wa-ookami-online/"
}