{
	"id": "CnL9CJkdkiSvL6b",
	"json": "{\"id\":\"CnL9CJkdkiSvL6b\",\"url\":\"https://www.brmangas.net/manga/junko-series-side-story-online/\",\"loadedUrl\":\"https://www.brmangas.net/manga/junko-series-side-story-online/\",\"uniqueKey\":\"https://www.brmangas.net/manga/junko-series-side-story-online\",\"method\":\"GET\",\"noRetry\":false,\"retryCount\":0,\"errorMessages\":[],\"headers\":{},\"userData\":{\"label\":\"manga_page\"},\"handledAt\":\"2022-09-27T18:54:42.477Z\"}",
	"method": "GET",
	"orderNo": null,
	"retryCount": 0,
	"uniqueKey": "https://www.brmangas.net/manga/junko-series-side-story-online",
	"url": "https://www.brmangas.net/manga/junko-series-side-story-online/"
}