{
	"id": "CO5ikqpv6o3CqTq",
	"json": "{\"id\":\"CO5ikqpv6o3CqTq\",\"url\":\"https://www.brmangas.net/manga/6mm-no-taboo-online-5/\",\"loadedUrl\":\"https://www.brmangas.net/manga/6mm-no-taboo-online-5/\",\"uniqueKey\":\"https://www.brmangas.net/manga/6mm-no-taboo-online-5\",\"method\":\"GET\",\"noRetry\":false,\"retryCount\":0,\"errorMessages\":[],\"headers\":{},\"userData\":{\"label\":\"manga_page\"},\"handledAt\":\"2022-09-27T18:53:03.219Z\"}",
	"method": "GET",
	"orderNo": null,
	"retryCount": 0,
	"uniqueKey": "https://www.brmangas.net/manga/6mm-no-taboo-online-5",
	"url": "https://www.brmangas.net/manga/6mm-no-taboo-online-5/"
}