{
	"id": "DIgwHWfV1WjHsnx",
	"json": "{\"id\":\"DIgwHWfV1WjHsnx\",\"url\":\"https://www.brmangas.net/manga/ueno-san-wa-bukiyou-online/\",\"loadedUrl\":\"https://www.brmangas.net/manga/ueno-san-wa-bukiyou-online/\",\"uniqueKey\":\"https://www.brmangas.net/manga/ueno-san-wa-bukiyou-online\",\"method\":\"GET\",\"noRetry\":false,\"retryCount\":0,\"errorMessages\":[],\"headers\":{},\"userData\":{\"label\":\"manga_page\"},\"handledAt\":\"2022-09-27T18:53:37.450Z\"}",
	"method": "GET",
	"orderNo": null,
	"retryCount": 0,
	"uniqueKey": "https://www.brmangas.net/manga/ueno-san-wa-bukiyou-online",
	"url": "https://www.brmangas.net/manga/ueno-san-wa-bukiyou-online/"
}