{
	"id": "i6lpO6uaASRIap3",
	"json": "{\"id\":\"i6lpO6uaASRIap3\",\"url\":\"https://www.brmangas.net/manga/1-x-12-online/\",\"loadedUrl\":\"https://www.brmangas.net/manga/1-x-12-online/\",\"uniqueKey\":\"https://www.brmangas.net/manga/1-x-12-online\",\"method\":\"GET\",\"noRetry\":false,\"retryCount\":0,\"errorMessages\":[],\"headers\":{},\"userData\":{\"label\":\"manga_page\"},\"handledAt\":\"2022-09-27T18:55:06.383Z\"}",
	"method": "GET",
	"orderNo": null,
	"retryCount": 0,
	"uniqueKey": "https://www.brmangas.net/manga/1-x-12-online",
	"url": "https://www.brmangas.net/manga/1-x-12-online/"
}