{
	"id": "iXm4rQOOoKULWKH",
	"json": "{\"id\":\"iXm4rQOOoKULWKH\",\"url\":\"https://www.brmangas.net/manga/nande-koko-ni-sensei-ga-online/\",\"loadedUrl\":\"https://www.brmangas.net/manga/nande-koko-ni-sensei-ga-online/\",\"uniqueKey\":\"https://www.brmangas.net/manga/nande-koko-ni-sensei-ga-online\",\"method\":\"GET\",\"noRetry\":false,\"retryCount\":0,\"errorMessages\":[],\"headers\":{},\"userData\":{\"label\":\"manga_page\"},\"handledAt\":\"2022-09-27T18:48:53.291Z\"}",
	"method": "GET",
	"orderNo": null,
	"retryCount": 0,
	"uniqueKey": "https://www.brmangas.net/manga/nande-koko-ni-sensei-ga-online",
	"url": "https://www.brmangas.net/manga/nande-koko-ni-sensei-ga-online/"
}