{
	"id": "LylpnnM9hdSFbLi",
	"json": "{\"id\":\"LylpnnM9hdSFbLi\",\"url\":\"https://www.brmangas.net/manga/agravity-boys-online/\",\"loadedUrl\":\"https://www.brmangas.net/manga/agravity-boys-online/\",\"uniqueKey\":\"https://www.brmangas.net/manga/agravity-boys-online\",\"method\":\"GET\",\"noRetry\":false,\"retryCount\":0,\"errorMessages\":[],\"headers\":{},\"userData\":{\"label\":\"manga_page\"},\"handledAt\":\"2022-09-27T18:52:34.283Z\"}",
	"method": "GET",
	"orderNo": null,
	"retryCount": 0,
	"uniqueKey": "https://www.brmangas.net/manga/agravity-boys-online",
	"url": "https://www.brmangas.net/manga/agravity-boys-online/"
}