{
	"id": "mKb6y8MLe0U8Mvd",
	"json": "{\"id\":\"mKb6y8MLe0U8Mvd\",\"url\":\"https://www.brmangas.net/manga/meguru-mirai-online/\",\"loadedUrl\":\"https://www.brmangas.net/manga/meguru-mirai-online/\",\"uniqueKey\":\"https://www.brmangas.net/manga/meguru-mirai-online\",\"method\":\"GET\",\"noRetry\":false,\"retryCount\":0,\"errorMessages\":[],\"headers\":{},\"userData\":{\"label\":\"manga_page\"},\"handledAt\":\"2022-09-27T18:49:51.184Z\"}",
	"method": "GET",
	"orderNo": null,
	"retryCount": 0,
	"uniqueKey": "https://www.brmangas.net/manga/meguru-mirai-online",
	"url": "https://www.brmangas.net/manga/meguru-mirai-online/"
}