{
	"id": "ngHuDVG7pSGc0Wc",
	"json": "{\"id\":\"ngHuDVG7pSGc0Wc\",\"url\":\"https://www.brmangas.net/manga/murenase-seton-gakuen-online/\",\"loadedUrl\":\"https://www.brmangas.net/manga/murenase-seton-gakuen-online/\",\"uniqueKey\":\"https://www.brmangas.net/manga/murenase-seton-gakuen-online\",\"method\":\"GET\",\"noRetry\":false,\"retryCount\":0,\"errorMessages\":[],\"headers\":{},\"userData\":{\"label\":\"manga_page\"},\"handledAt\":\"2022-09-27T18:52:57.755Z\"}",
	"method": "GET",
	"orderNo": null,
	"retryCount": 0,
	"uniqueKey": "https://www.brmangas.net/manga/murenase-seton-gakuen-online",
	"url": "https://www.brmangas.net/manga/murenase-seton-gakuen-online/"
}