{
	"id": "NH8PmjDw2Hwj2fp",
	"json": "{\"id\":\"NH8PmjDw2Hwj2fp\",\"url\":\"https://www.brmangas.net/lista-de-manga/page/134/\",\"loadedUrl\":\"https://www.brmangas.net/lista-de-manga/page/134/\",\"uniqueKey\":\"https://www.brmangas.net/lista-de-manga/page/134\",\"method\":\"GET\",\"noRetry\":false,\"retryCount\":0,\"errorMessages\":[],\"headers\":{},\"userData\":{\"label\":\"manga_list_page\"},\"handledAt\":\"2022-09-27T18:54:20.133Z\"}",
	"method": "GET",
	"orderNo": null,
	"retryCount": 0,
	"uniqueKey": "https://www.brmangas.net/lista-de-manga/page/134",
	"url": "https://www.brmangas.net/lista-de-manga/page/134/"
}