{
	"id": "NvFRyeiMQ90HVs0",
	"json": "{\"id\":\"NvFRyeiMQ90HVs0\",\"url\":\"https://www.brmangas.net/manga/maou-sama-retry-online/\",\"loadedUrl\":\"https://www.brmangas.net/manga/maou-sama-retry-online/\",\"uniqueKey\":\"https://www.brmangas.net/manga/maou-sama-retry-online\",\"method\":\"GET\",\"noRetry\":false,\"retryCount\":0,\"errorMessages\":[],\"headers\":{},\"userData\":{\"label\":\"manga_page\"},\"handledAt\":\"2022-09-27T18:52:04.242Z\"}",
	"method": "GET",
	"orderNo": null,
	"retryCount": 0,
	"uniqueKey": "https://www.brmangas.net/manga/maou-sama-retry-online",
	"url": "https://www.brmangas.net/manga/maou-sama-retry-online/"
}