{
	"id": "nwGDmsDbrfZo1Ox",
	"json": "{\"id\":\"nwGDmsDbrfZo1Ox\",\"url\":\"https://www.brmangas.net/manga/re-cervin-online/\",\"loadedUrl\":\"https://www.brmangas.net/manga/re-cervin-online/\",\"uniqueKey\":\"https://www.brmangas.net/manga/re-cervin-online\",\"method\":\"GET\",\"noRetry\":false,\"retryCount\":0,\"errorMessages\":[],\"headers\":{},\"userData\":{\"label\":\"manga_page\"},\"handledAt\":\"2022-09-27T18:52:32.707Z\"}",
	"method": "GET",
	"orderNo": null,
	"retryCount": 0,
	"uniqueKey": "https://www.brmangas.net/manga/re-cervin-online",
	"url": "https://www.brmangas.net/manga/re-cervin-online/"
}