{
	"id": "OpJDotu1Vflp8sM",
	"json": "{\"id\":\"OpJDotu1Vflp8sM\",\"url\":\"https://www.brmangas.net/manga/oyasumi-punpun-online/\",\"loadedUrl\":\"https://www.brmangas.net/manga/oyasumi-punpun-online/\",\"uniqueKey\":\"https://www.brmangas.net/manga/oyasumi-punpun-online\",\"method\":\"GET\",\"noRetry\":false,\"retryCount\":0,\"errorMessages\":[],\"headers\":{},\"userData\":{\"label\":\"manga_page\"},\"handledAt\":\"2022-09-27T18:48:46.486Z\"}",
	"method": "GET",
	"orderNo": null,
	"retryCount": 0,
	"uniqueKey": "https://www.brmangas.net/manga/oyasumi-punpun-online",
	"url": "https://www.brmangas.net/manga/oyasumi-punpun-online/"
}