{
	"id": "QHIdSFuM8VC6ka2",
	"json": "{\"id\":\"QHIdSFuM8VC6ka2\",\"url\":\"https://www.brmangas.net/manga/gad-sfortunato-online/\",\"loadedUrl\":\"https://www.brmangas.net/manga/gad-sfortunato-online/\",\"uniqueKey\":\"https://www.brmangas.net/manga/gad-sfortunato-online\",\"method\":\"GET\",\"noRetry\":false,\"retryCount\":0,\"errorMessages\":[],\"headers\":{},\"userData\":{\"label\":\"manga_page\"},\"handledAt\":\"2022-09-27T18:51:16.900Z\"}",
	"method": "GET",
	"orderNo": null,
	"retryCount": 0,
	"uniqueKey": "https://www.brmangas.net/manga/gad-sfortunato-online",
	"url": "https://www.brmangas.net/manga/gad-sfortunato-online/"
}