{
	"id": "R6djccAPDdz8Jx7",
	"json": "{\"id\":\"R6djccAPDdz8Jx7\",\"url\":\"https://www.brmangas.net/manga/cafe-relish-ni-oide-online/\",\"loadedUrl\":\"https://www.brmangas.net/manga/cafe-relish-ni-oide-online/\",\"uniqueKey\":\"https://www.brmangas.net/manga/cafe-relish-ni-oide-online\",\"method\":\"GET\",\"noRetry\":false,\"retryCount\":0,\"errorMessages\":[],\"headers\":{},\"userData\":{\"label\":\"manga_page\"},\"handledAt\":\"2022-09-27T18:53:16.234Z\"}",
	"method": "GET",
	"orderNo": null,
	"retryCount": 0,
	"uniqueKey": "https://www.brmangas.net/manga/cafe-relish-ni-oide-online",
	"url": "https://www.brmangas.net/manga/cafe-relish-ni-oide-online/"
}