{
	"id": "rhWTzcPIJwyHXj8",
	"json": "{\"id\":\"rhWTzcPIJwyHXj8\",\"url\":\"https://www.brmangas.net/manga/3x3-eyes-online/\",\"loadedUrl\":\"https://www.brmangas.net/manga/3x3-eyes-online/\",\"uniqueKey\":\"https://www.brmangas.net/manga/3x3-eyes-online\",\"method\":\"GET\",\"noRetry\":false,\"retryCount\":0,\"errorMessages\":[],\"headers\":{},\"userData\":{\"label\":\"manga_page\"},\"handledAt\":\"2022-09-27T18:53:29.221Z\"}",
	"method": "GET",
	"orderNo": null,
	"retryCount": 0,
	"uniqueKey": "https://www.brmangas.net/manga/3x3-eyes-online",
	"url": "https://www.brmangas.net/manga/3x3-eyes-online/"
}