{
	"id": "rSl36qu9PFg4Z2t",
	"json": "{\"id\":\"rSl36qu9PFg4Z2t\",\"url\":\"https://www.brmangas.net/manga/daisuki-no-yukue-online/\",\"loadedUrl\":\"https://www.brmangas.net/manga/daisuki-no-yukue-online/\",\"uniqueKey\":\"https://www.brmangas.net/manga/daisuki-no-yukue-online\",\"method\":\"GET\",\"noRetry\":false,\"retryCount\":0,\"errorMessages\":[],\"headers\":{},\"userData\":{\"label\":\"manga_page\"},\"handledAt\":\"2022-09-27T18:53:11.775Z\"}",
	"method": "GET",
	"orderNo": null,
	"retryCount": 0,
	"uniqueKey": "https://www.brmangas.net/manga/daisuki-no-yukue-online",
	"url": "https://www.brmangas.net/manga/daisuki-no-yukue-online/"
}