{
	"id": "Sd0LMFY6O9JHwdg",
	"json": "{\"id\":\"Sd0LMFY6O9JHwdg\",\"url\":\"https://www.brmangas.net/manga/jappa-no-amane-online/\",\"loadedUrl\":\"https://www.brmangas.net/manga/jappa-no-amane-online/\",\"uniqueKey\":\"https://www.brmangas.net/manga/jappa-no-amane-online\",\"method\":\"GET\",\"noRetry\":false,\"retryCount\":0,\"errorMessages\":[],\"headers\":{},\"userData\":{\"label\":\"manga_page\"},\"handledAt\":\"2022-09-27T18:54:44.784Z\"}",
	"method": "GET",
	"orderNo": null,
	"retryCount": 0,
	"uniqueKey": "https://www.brmangas.net/manga/jappa-no-amane-online",
	"url": "https://www.brmangas.net/manga/jappa-no-amane-online/"
}