{
	"id": "srVAlDjyjkdNUMm",
	"json": "{\"id\":\"srVAlDjyjkdNUMm\",\"url\":\"https://www.brmangas.net/manga/serman-online/\",\"loadedUrl\":\"https://www.brmangas.net/manga/serman-online/\",\"uniqueKey\":\"https://www.brmangas.net/manga/serman-online\",\"method\":\"GET\",\"noRetry\":false,\"retryCount\":0,\"errorMessages\":[],\"headers\":{},\"userData\":{\"label\":\"manga_page\"},\"handledAt\":\"2022-09-27T18:54:49.548Z\"}",
	"method": "GET",
	"orderNo": null,
	"retryCount": 0,
	"uniqueKey": "https://www.brmangas.net/manga/serman-online",
	"url": "https://www.brmangas.net/manga/serman-online/"
}