{
	"id": "TnDNcHqusaJKG2Y",
	"json": "{\"id\":\"TnDNcHqusaJKG2Y\",\"url\":\"https://www.brmangas.net/manga/aishite-kudasai-sensei-online/\",\"loadedUrl\":\"https://www.brmangas.net/manga/aishite-kudasai-sensei-online/\",\"uniqueKey\":\"https://www.brmangas.net/manga/aishite-kudasai-sensei-online\",\"method\":\"GET\",\"noRetry\":false,\"retryCount\":0,\"errorMessages\":[],\"headers\":{},\"userData\":{\"label\":\"manga_page\"},\"handledAt\":\"2022-09-27T18:55:07.346Z\"}",
	"method": "GET",
	"orderNo": null,
	"retryCount": 0,
	"uniqueKey": "https://www.brmangas.net/manga/aishite-kudasai-sensei-online",
	"url": "https://www.brmangas.net/manga/aishite-kudasai-sensei-online/"
}