{
	"id": "u7oNXvMd18gibIe",
	"json": "{\"id\":\"u7oNXvMd18gibIe\",\"url\":\"https://www.brmangas.net/manga/hitorijime-theory-online/\",\"loadedUrl\":\"https://www.brmangas.net/manga/hitorijime-theory-online/\",\"uniqueKey\":\"https://www.brmangas.net/manga/hitorijime-theory-online\",\"method\":\"GET\",\"noRetry\":false,\"retryCount\":0,\"errorMessages\":[],\"headers\":{},\"userData\":{\"label\":\"manga_page\"},\"handledAt\":\"2022-09-27T18:54:15.217Z\"}",
	"method": "GET",
	"orderNo": null,
	"retryCount": 0,
	"uniqueKey": "https://www.brmangas.net/manga/hitorijime-theory-online",
	"url": "https://www.brmangas.net/manga/hitorijime-theory-online/"
}