{
	"id": "V1nV3V8vYmYvrZ1",
	"json": "{\"id\":\"V1nV3V8vYmYvrZ1\",\"url\":\"https://www.brmangas.net/manga/niehime-to-kemono-no-ou-online/\",\"loadedUrl\":\"https://www.brmangas.net/manga/niehime-to-kemono-no-ou-online/\",\"uniqueKey\":\"https://www.brmangas.net/manga/niehime-to-kemono-no-ou-online\",\"method\":\"GET\",\"noRetry\":false,\"retryCount\":0,\"errorMessages\":[],\"headers\":{},\"userData\":{\"label\":\"manga_page\"},\"handledAt\":\"2022-09-27T18:52:53.591Z\"}",
	"method": "GET",
	"orderNo": null,
	"retryCount": 0,
	"uniqueKey": "https://www.brmangas.net/manga/niehime-to-kemono-no-ou-online",
	"url": "https://www.brmangas.net/manga/niehime-to-kemono-no-ou-online/"
}