{
	"id": "VD61vZjRjvWR4DM",
	"json": "{\"id\":\"VD61vZjRjvWR4DM\",\"url\":\"https://www.brmangas.net/manga/gekuji-high-school-online/\",\"loadedUrl\":\"https://www.brmangas.net/manga/gekuji-high-school-online/\",\"uniqueKey\":\"https://www.brmangas.net/manga/gekuji-high-school-online\",\"method\":\"GET\",\"noRetry\":false,\"retryCount\":0,\"errorMessages\":[],\"headers\":{},\"userData\":{\"label\":\"manga_page\"},\"handledAt\":\"2022-09-27T18:55:12.860Z\"}",
	"method": "GET",
	"orderNo": null,
	"retryCount": 0,
	"uniqueKey": "https://www.brmangas.net/manga/gekuji-high-school-online",
	"url": "https://www.brmangas.net/manga/gekuji-high-school-online/"
}