{
	"id": "VLfZ13m1R61EVC4",
	"json": "{\"id\":\"VLfZ13m1R61EVC4\",\"url\":\"https://www.brmangas.net/manga/crimson-skies-online/\",\"loadedUrl\":\"https://www.brmangas.net/manga/crimson-skies-online/\",\"uniqueKey\":\"https://www.brmangas.net/manga/crimson-skies-online\",\"method\":\"GET\",\"noRetry\":false,\"retryCount\":0,\"errorMessages\":[],\"headers\":{},\"userData\":{\"label\":\"manga_page\"},\"handledAt\":\"2022-09-27T18:53:27.843Z\"}",
	"method": "GET",
	"orderNo": null,
	"retryCount": 0,
	"uniqueKey": "https://www.brmangas.net/manga/crimson-skies-online",
	"url": "https://www.brmangas.net/manga/crimson-skies-online/"
}