{
	"id": "VXuoVsj0wUBigfb",
	"json": "{\"id\":\"VXuoVsj0wUBigfb\",\"url\":\"https://www.brmangas.net/manga/anti-gods-dragon-system-online/\",\"loadedUrl\":\"https://www.brmangas.net/manga/anti-gods-dragon-system-online/\",\"uniqueKey\":\"https://www.brmangas.net/manga/anti-gods-dragon-system-online\",\"method\":\"GET\",\"noRetry\":false,\"retryCount\":0,\"errorMessages\":[],\"headers\":{},\"userData\":{\"label\":\"manga_page\"},\"handledAt\":\"2022-09-27T18:50:31.022Z\"}",
	"method": "GET",
	"orderNo": null,
	"retryCount": 0,
	"uniqueKey": "https://www.brmangas.net/manga/anti-gods-dragon-system-online",
	"url": "https://www.brmangas.net/manga/anti-gods-dragon-system-online/"
}