{
	"id": "ZB5OfUFIeZRYr6V",
	"json": "{\"id\":\"ZB5OfUFIeZRYr6V\",\"url\":\"https://www.brmangas.net/manga/nukenai-seiken-chan-online/\",\"loadedUrl\":\"https://www.brmangas.net/manga/nukenai-seiken-chan-online/\",\"uniqueKey\":\"https://www.brmangas.net/manga/nukenai-seiken-chan-online\",\"method\":\"GET\",\"noRetry\":false,\"retryCount\":0,\"errorMessages\":[],\"headers\":{},\"userData\":{\"label\":\"manga_page\"},\"handledAt\":\"2022-09-27T18:51:57.945Z\"}",
	"method": "GET",
	"orderNo": null,
	"retryCount": 0,
	"uniqueKey": "https://www.brmangas.net/manga/nukenai-seiken-chan-online",
	"url": "https://www.brmangas.net/manga/nukenai-seiken-chan-online/"
}